simclr/__init__.py
simclr/simclr.py
simclr/modules/__init__.py
simclr/modules/gather.py
simclr/modules/identity.py
simclr/modules/lars.py
simclr/modules/logistic_regression.py
simclr/modules/nt_xent.py
simclr/modules/resnet.py
simclr/modules/resnet_hacks.py
simclr/modules/sync_batchnorm/__init__.py
simclr/modules/sync_batchnorm/batchnorm.py
simclr/modules/sync_batchnorm/batchnorm_reimpl.py
simclr/modules/sync_batchnorm/comm.py
simclr/modules/sync_batchnorm/replicate.py
simclr/modules/sync_batchnorm/unittest.py
simclr/modules/transformations/__init__.py
simclr/modules/transformations/simclr.py
utils/__init__.py
utils/yaml_config_hook.py
simclr-1.0.2.dist-info/LICENSE
simclr-1.0.2.dist-info/METADATA
simclr-1.0.2.dist-info/WHEEL
simclr-1.0.2.dist-info/top_level.txt
simclr-1.0.2.dist-info/RECORD
