Metadata-Version: 2.1
Name: simclr
Version: 1.0.2
Summary: PyTorch implementation of SimCLR: A Simple Framework for Contrastive Learning of Visual Representations by T. Chen et al.
Home-page: https://github.com/spijkervet/SimCLR
Author: Janne Spijkervet
Author-email: janne.spijkervet@gmail.com
License: MIT
Platform: UNKNOWN
Classifier: License :: OSI Approved :: MIT License
Classifier: Programming Language :: Python
Classifier: Programming Language :: Python :: 3
Classifier: Programming Language :: Python :: 3.6
Classifier: Programming Language :: Python :: Implementation :: CPython
Classifier: Programming Language :: Python :: Implementation :: PyPy
Requires-Python: >=3.6.0
Requires-Dist: torch
Requires-Dist: torchvision
Requires-Dist: pyyaml
Provides-Extra: fancy_feature
Requires-Dist: tensorboard ; extra == 'fancy_feature'
